{
    "key": "group_610f8a1b421ef",
    "title": "Устройство LED-экранов",
    "fields": [
        {
            "key": "field_610f8a2b8db65",
            "label": "Заголовок",
            "name": "display_device_title",
            "type": "text",
            "instructions": "",
            "required": 0,
            "conditional_logic": 0,
            "wrapper": {
                "width": "",
                "class": "",
                "id": ""
            },
            "default_value": "",
            "placeholder": "",
            "prepend": "",
            "append": "",
            "maxlength": ""
        }
    ],
    "location": [
        [
            {
                "param": "page",
                "operator": "==",
                "value": "9"
            }
        ],
        [
            {
                "param": "page",
                "operator": "==",
                "value": "11"
            }
        ]
    ],
    "menu_order": 4,
    "position": "normal",
    "style": "default",
    "label_placement": "top",
    "instruction_placement": "label",
    "hide_on_screen": "",
    "active": true,
    "description": "",
    "modified": 1628427530
}